bigdl/__init__.py
bigdl/chronos/__init__.py
bigdl/chronos/utils.py
bigdl/chronos/autots/__init__.py
bigdl/chronos/autots/autotsestimator.py
bigdl/chronos/autots/tspipeline.py
bigdl/chronos/autots/utils.py
bigdl/chronos/autots/deprecated/__init__.py
bigdl/chronos/autots/deprecated/forecast.py
bigdl/chronos/autots/deprecated/config/__init__.py
bigdl/chronos/autots/deprecated/config/base.py
bigdl/chronos/autots/deprecated/config/recipe.py
bigdl/chronos/autots/deprecated/feature/__init__.py
bigdl/chronos/autots/deprecated/feature/abstract.py
bigdl/chronos/autots/deprecated/feature/identity_transformer.py
bigdl/chronos/autots/deprecated/feature/time_sequence.py
bigdl/chronos/autots/deprecated/feature/utils.py
bigdl/chronos/autots/deprecated/model/time_sequence.py
bigdl/chronos/autots/deprecated/pipeline/__init__.py
bigdl/chronos/autots/deprecated/pipeline/base.py
bigdl/chronos/autots/deprecated/pipeline/parameters.py
bigdl/chronos/autots/deprecated/pipeline/time_sequence.py
bigdl/chronos/autots/deprecated/preprocessing/utils.py
bigdl/chronos/autots/deprecated/preprocessing/impute/LastFill.py
bigdl/chronos/autots/deprecated/preprocessing/impute/__init__.py
bigdl/chronos/autots/deprecated/preprocessing/impute/abstract.py
bigdl/chronos/autots/deprecated/preprocessing/impute/impute.py
bigdl/chronos/autots/deprecated/regression/__init__.py
bigdl/chronos/autots/deprecated/regression/base_predictor.py
bigdl/chronos/autots/deprecated/regression/time_sequence_predictor.py
bigdl/chronos/autots/model/__init__.py
bigdl/chronos/autots/model/auto_arima.py
bigdl/chronos/autots/model/auto_lstm.py
bigdl/chronos/autots/model/auto_prophet.py
bigdl/chronos/autots/model/auto_seq2seq.py
bigdl/chronos/autots/model/auto_tcn.py
bigdl/chronos/autots/model/base_automodel.py
bigdl/chronos/data/__init__.py
bigdl/chronos/data/repo_dataset.py
bigdl/chronos/data/tsdataset.py
bigdl/chronos/data/experimental/__init__.py
bigdl/chronos/data/experimental/utils.py
bigdl_chronos_spark321-2.1.0b202207291.dist-info/METADATA
bigdl_chronos_spark321-2.1.0b202207291.dist-info/WHEEL
bigdl_chronos_spark321-2.1.0b202207291.dist-info/dependency_links.txt
bigdl_chronos_spark321-2.1.0b202207291.dist-info/top_level.txt
bigdl_chronos_spark321-2.1.0b202207291.dist-info/RECORD
