Metadata-Version: 2.1
Name: bigdl-chronos-spark321
Version: 2.1.0b202207291
Summary: Scalable time series analysis using AutoML
Home-page: https://github.com/intel-analytics/BigDL
Author: BigDL Authors
Author-email: bigdl-user-group@googlegroups.com
License: Apache License, Version 2.0
Platform: mac
Platform: linux
Classifier: License :: OSI Approved :: Apache Software License
Classifier: Programming Language :: Python :: 3
Classifier: Programming Language :: Python :: 3.7
Classifier: Programming Language :: Python :: Implementation :: CPython
Requires-Dist: bigdl-orca-spark321 (==2.1.0b202207291)
Requires-Dist: bigdl-nano[pytorch] (==2.1.0b202207291)
Requires-Dist: pandas (<1.3.0,>=1.0.5)
Requires-Dist: scikit-learn (<=1.0.2,>=0.22.0)
Requires-Dist: onnx (<=1.11.0,>=1.8.0)
Requires-Dist: onnxruntime (<=1.11.1,>=1.6.0)
Provides-Extra: all
Requires-Dist: bigdl-orca-spark321[automl] (==2.1.0b202207291) ; extra == 'all'
